[
    {
        "D": 20,
        "V": 10,
        "K": 2,
        "N": 20,
        "alpha0": 1,
        "gamma0": 1,
        "id": 1
    },
    {
        "D": 100,
        "V": 10,
        "K": 2,
        "N": 20,
        "alpha0": 1,
        "gamma0": 1,
        "id": 2
    },
    {
        "D": 20,
        "V": 50,
        "K": 2,
        "N": 20,
        "alpha0": 1,
        "gamma0": 1,
        "id": 3
    },
    {
        "D": 100,
        "V": 50,
        "K": 2,
        "N": 20,
        "alpha0": 1,
        "gamma0": 1,
        "id": 4
    },
    {
        "D": 20,
        "V": 10,
        "K": 2,
        "N": 50,
        "alpha0": 1,
        "gamma0": 1,
        "id": 5
    },
    {
        "D": 100,
        "V": 10,
        "K": 2,
        "N": 50,
        "alpha0": 1,
        "gamma0": 1,
        "id": 6
    },
    {
        "D": 20,
        "V": 50,
        "K": 2,
        "N": 50,
        "alpha0": 1,
        "gamma0": 1,
        "id": 7
    },
    {
        "D": 100,
        "V": 50,
        "K": 2,
        "N": 50,
        "alpha0": 1,
        "gamma0": 1,
        "id": 8
    },
    {
        "D": 20,
        "V": 10,
        "K": 2,
        "N": 100,
        "alpha0": 1,
        "gamma0": 1,
        "id": 9
    },
    {
        "D": 100,
        "V": 10,
        "K": 2,
        "N": 100,
        "alpha0": 1,
        "gamma0": 1,
        "id": 10
    },
    {
        "D": 20,
        "V": 50,
        "K": 2,
        "N": 100,
        "alpha0": 1,
        "gamma0": 1,
        "id": 11
    },
    {
        "D": 100,
        "V": 50,
        "K": 2,
        "N": 100,
        "alpha0": 1,
        "gamma0": 1,
        "id": 12
    }
]
